domtag/__init__.py
domtag/common.py
domtag/utils/__init__.py
domtag/utils/enums.py
domtag/utils/storage_config.py
domtag/xbrl_parser/__init__.py
domtag/xbrl_parser/calculation_arc_to_tree.py
domtag/xbrl_parser/concepts.py
domtag/xbrl_parser/definition_arc_to_tree.py
domtag/xbrl_parser/from_zip_to_json.py
domtag/xbrl_parser/xbrl_gaap_parser.py
domtag-0.3.12.dist-info/METADATA
domtag-0.3.12.dist-info/WHEEL
domtag-0.3.12.dist-info/top_level.txt
domtag-0.3.12.dist-info/RECORD
