Metadata-Version: 2.1
Name: domtag
Version: 0.3.12
Home-page: https://github.com/cognaize/domtag
Author: cognaize
Requires-Dist: beautifulsoup4
Requires-Dist: numpy
